uv_ship/__init__.py
uv_ship/changelogger.py
uv_ship/cli.py
uv_ship/commands/__init__.py
uv_ship/commands/general.py
uv_ship/commands/git.py
uv_ship/commands/run.py
uv_ship/commands/versions.py
uv_ship/config/__init__.py
uv_ship/config/config_loader.py
uv_ship/config/default_config.toml
uv_ship/messages.py
uv_ship/preflight.py
uv_ship/resources/__init__.py
uv_ship/resources/ansi.json
uv_ship/resources/rich_click_theme.py
uv_ship/resources/symbols.json
uv_ship/workflows.py
uv_ship-0.8.0.dist-info/WHEEL
uv_ship-0.8.0.dist-info/entry_points.txt
uv_ship-0.8.0.dist-info/METADATA
uv_ship-0.8.0.dist-info/RECORD
