Metadata-Version: 2.3
Name: uv-ship
Version: 0.8.0
Summary: a release workflow streamliner for uv managed python projects
License: MIT License
Requires-Dist: tomli>=2.2 ; python_full_version < '3.11'
Requires-Dist: rich-click>=1.9.1
Requires-Python: >=3.10
